councilmatic_core/__init__.py
councilmatic_core/admin.py
councilmatic_core/apps.py
councilmatic_core/feeds.py
councilmatic_core/haystack_indexes.py
councilmatic_core/models.py
councilmatic_core/settings.py
councilmatic_core/urls.py
councilmatic_core/utils.py
councilmatic_core/views.py
councilmatic_core/management/__init__.py
councilmatic_core/management/commands/__init__.py
councilmatic_core/management/commands/convert_attachment_text.py
councilmatic_core/management/commands/convert_rtf.py
councilmatic_core/management/commands/import_shapes.py
councilmatic_core/management/commands/make_fixtures.py
councilmatic_core/management/commands/refresh_pic.py
councilmatic_core/management/commands/update_headshots.py
councilmatic_core/migrations/0001_initial.py
councilmatic_core/migrations/0002_auto_20151210_1342.py
councilmatic_core/migrations/0003_auto_20151214_1222.py
councilmatic_core/migrations/0004_auto_20151214_1413.py
councilmatic_core/migrations/0005_auto_20151215_1430.py
councilmatic_core/migrations/0006_bill_subject.py
councilmatic_core/migrations/0007_auto_20151223_1150.py
councilmatic_core/migrations/0008_bill_ocr_full_text.py
councilmatic_core/migrations/0009_bill_updated_at.py
councilmatic_core/migrations/0010_auto_20160120_1248.py
councilmatic_core/migrations/0011_auto_20161012_1204.py
councilmatic_core/migrations/0011_auto_20161013_1541.py
councilmatic_core/migrations/0012_auto_20161012_1218.py
councilmatic_core/migrations/0013_auto_20161012_1414.py
councilmatic_core/migrations/0014_auto_20161012_1419.py
councilmatic_core/migrations/0015_auto_20161012_1626.py
councilmatic_core/migrations/0016_auto_20161013_1140.py
councilmatic_core/migrations/0017_auto_20161013_1656.py
councilmatic_core/migrations/0018_auto_20161013_1656.py
councilmatic_core/migrations/0019_auto_20161013_1702.py
councilmatic_core/migrations/0020_auto_20161013_1704.py
councilmatic_core/migrations/0021_auto_20161014_1349.py
councilmatic_core/migrations/0022_auto_20161014_1350.py
django_councilmatic-3.3.dist-info/LICENSE
django_councilmatic-3.3.dist-info/METADATA
django_councilmatic-3.3.dist-info/WHEEL
django_councilmatic-3.3.dist-info/top_level.txt
django_councilmatic-3.3.dist-info/RECORD
