Metadata-Version: 2.1
Name: django-councilmatic
Version: 3.3
Summary: Core functions for councilmatic.org family
Home-page: http://councilmatic.org/
Author: DataMade, LLC
Author-email: info@datamade.us
License: MIT License
Classifier: Environment :: Web Environment
Classifier: Framework :: Django
Classifier: Intended Audience :: Developers
Classifier: License :: OSI Approved :: BSD License
Classifier: Operating System :: OS Independent
Classifier: Programming Language :: Python
Classifier: Programming Language :: Python :: 3.7
Classifier: Programming Language :: Python :: 3.8
Classifier: Programming Language :: Python :: 3.9
Classifier: Programming Language :: Python :: 3.10
Classifier: Programming Language :: Python :: 3.11
Classifier: Topic :: Internet :: WWW/HTTP
Classifier: Topic :: Internet :: WWW/HTTP :: Dynamic Content
Requires-Python: >=3.6
License-File: LICENSE
Requires-Dist: requests >=2.20
Requires-Dist: opencivicdata >=3.1.0
Requires-Dist: pytz >=2015.4
Requires-Dist: django-haystack <3.3,>=3.2
Requires-Dist: Django <3.3,>=3.2
Requires-Dist: django-proxy-overrides >=0.2.1
Requires-Dist: python-dateutil <2.8,>=2.7
Requires-Dist: psycopg2-binary >=2.9.5
Requires-Dist: django-adv-cache-tag ==1.1.2
Requires-Dist: boto ==2.38.0
Requires-Dist: tqdm
Provides-Extra: convert_docs
Requires-Dist: textract ; extra == 'convert_docs'
